sidera/__init__.py
sidera/__main__.py
sidera/main.py
sidera/config/__init__.py
sidera/config/args_parser.py
sidera/config/constants.py
sidera/config/models.py
sidera/plugin/__init__.py
sidera/plugin/hook_impl.py
sidera/plugin/hook_specs.py
sidera/plugin/logger.py
sidera/plugin/plugin_hooks.py
sidera/plugin/plugin_registry.py
sidera/scenario/__init__.py
sidera/scenario/factory.py
sidera/scenario/signal_func.py
sidera/scenario/models/__init__.py
sidera/scenario/models/input.py
sidera/scenario/models/output.py
sidera/scenario/models/scenario.py
sidera/scenario/models/scene.py
sidera/scenario/models/signal.py
sidera/scenario/models/state.py
sidera/scenario/models/story.py
sidera/scenario/models/value.py
sidera/task/__init__.py
sidera/task/worker.py
sidera-0.1.0a0.dist-info/METADATA
sidera-0.1.0a0.dist-info/WHEEL
sidera-0.1.0a0.dist-info/entry_points.txt
sidera-0.1.0a0.dist-info/licenses/LICENSE
sidera-0.1.0a0.dist-info/RECORD
